randword/__init__.py
randword/cli.py
randword/rand_letter.py
randword/rand_name.py
randword/rand_other.py
randword/rand_place.py
randword/rand_word.py
randword/utilities.py
randword/data/names/female_names.txt
randword/data/names/male_names.txt
randword/data/names/surnames.txt
randword/data/other/magic_8ball_answers.txt
randword/data/parts_of_speech/adj.txt
randword/data/parts_of_speech/adv.txt
randword/data/parts_of_speech/conj.txt
randword/data/parts_of_speech/interj.txt
randword/data/parts_of_speech/noun.txt
randword/data/parts_of_speech/prep.txt
randword/data/parts_of_speech/pron.txt
randword/data/parts_of_speech/verb.txt
randword/data/places/cities.txt
randword/data/places/countries.txt
randword-2.11.4.dist-info/licenses/LICENSE.txt
randword-2.11.4.dist-info/METADATA
randword-2.11.4.dist-info/WHEEL
randword-2.11.4.dist-info/entry_points.txt
randword-2.11.4.dist-info/top_level.txt
randword-2.11.4.dist-info/RECORD
