Metadata-Version: 2.4
Name: randword
Version: 2.11.4
Summary: The Python package for generating random English words
Author-email: "Artyom Bezmenov (8nhuman)" <artem.bezmenov02@gmail.com>
License-Expression: MIT
Project-URL: Bug Tracker, https://github.com/8nhuman8/randword/issues
Project-URL: Source Code, https://github.com/8nhuman8/randword
Project-URL: Documentation, https://randword.readthedocs.io/en/stable/
Project-URL: Download, https://github.com/8nhuman8/randword/archive/2.11.3.tar.gz
Project-URL: Homepage, https://github.com/8nhuman8/randword
Keywords: python,package,python-package,random,word,words,generator,generation,random-word,random-words,random-word-generator,random-word-generation,english,english-word,english-words
Classifier: Programming Language :: Python :: 3
Classifier: Programming Language :: Python :: 3.7
Classifier: Development Status :: 5 - Production/Stable
Classifier: Topic :: Software Development :: Libraries :: Python Modules
Classifier: Intended Audience :: Developers
Classifier: Operating System :: OS Independent
Requires-Python: >=3.7
License-File: LICENSE.txt
Dynamic: license-file
